[
  {
    "trend_arrow": "FLAT", 
    "system_time": "2016-10-22T04:09:53", 
    "direction": "Flat", 
    "sgv": 80, 
    "display_time": "2016-10-21T21:10:15", 
    "date": 1477109415000.0, 
    "dateString": "2016-10-21T21:10:15", 
    "device": "openaps://cgm", 
    "type": "sgv", 
    "glucose": 80
  }, 
  {
    "trend_arrow": "FLAT", 
    "system_time": "2016-10-22T04:04:45", 
    "direction": "Flat", 
    "sgv": 74, 
    "display_time": "2016-10-21T21:05:08", 
    "date": 1477109108000.0, 
    "dateString": "2016-10-21T21:05:08", 
    "device": "openaps://cgm", 
    "type": "sgv", 
    "glucose": 74
  }, 
  {
    "trend_arrow": "FLAT", 
    "system_time": "2016-10-22T03:59:45", 
    "direction": "Flat", 
    "sgv": 72, 
    "display_time": "2016-10-21T21:00:07", 
    "date": 1477108807000.0, 
    "dateString": "2016-10-21T21:00:07", 
    "device": "openaps://cgm", 
    "type": "sgv", 
    "glucose": 72
  }, 
  {
    "trend_arrow": "FLAT", 
    "system_time": "2016-10-22T03:54:51", 
    "direction": "Flat", 
    "sgv": 72, 
    "display_time": "2016-10-21T20:55:13", 
    "date": 1477108513000.0, 
    "dateString": "2016-10-21T20:55:13", 
    "device": "openaps://cgm", 
    "type": "sgv", 
    "glucose": 72
  }, 
  {
    "trend_arrow": "FLAT", 
    "system_time": "2016-10-22T03:49:52", 
    "direction": "Flat", 
    "sgv": 76, 
    "display_time": "2016-10-21T20:50:14", 
    "date": 1477108214000.0, 
    "dateString": "2016-10-21T20:50:14", 
    "device": "openaps://cgm", 
    "type": "sgv", 
    "glucose": 76
  }, 
  {
    "trend_arrow": "FLAT", 
    "system_time": "2016-10-22T03:34:50", 
    "direction": "Flat", 
    "sgv": 91, 
    "display_time": "2016-10-21T20:35:12", 
    "date": 1477107312000.0, 
    "dateString": "2016-10-21T20:35:12", 
    "device": "openaps://cgm", 
    "type": "sgv", 
    "glucose": 91
  }, 
  {
    "trend_arrow": "FLAT", 
    "system_time": "2016-10-22T03:29:50", 
    "direction": "Flat", 
    "sgv": 88, 
    "display_time": "2016-10-21T20:30:13", 
    "date": 1477107013000.0, 
    "dateString": "2016-10-21T20:30:13", 
    "device": "openaps://cgm", 
    "type": "sgv", 
    "glucose": 88
  }, 
  {
    "trend_arrow": "FLAT", 
    "system_time": "2016-10-22T03:24:49", 
    "direction": "Flat", 
    "sgv": 88, 
    "display_time": "2016-10-21T20:25:11", 
    "date": 1477106711000.0, 
    "dateString": "2016-10-21T20:25:11", 
    "device": "openaps://cgm", 
    "type": "sgv", 
    "glucose": 88
  }, 
  {
    "trend_arrow": "FLAT", 
    "system_time": "2016-10-22T03:19:55", 
    "direction": "Flat", 
    "sgv": 92, 
    "display_time": "2016-10-21T20:20:17", 
    "date": 1477106417000.0, 
    "dateString": "2016-10-21T20:20:17", 
    "device": "openaps://cgm", 
    "type": "sgv", 
    "glucose": 92
  }, 
  {
    "trend_arrow": "FLAT", 
    "system_time": "2016-10-22T03:14:51", 
    "direction": "Flat", 
    "sgv": 95, 
    "display_time": "2016-10-21T20:15:14", 
    "date": 1477106114000.0, 
    "dateString": "2016-10-21T20:15:14", 
    "device": "openaps://cgm", 
    "type": "sgv", 
    "glucose": 95
  }, 
  {
    "trend_arrow": "FLAT", 
    "system_time": "2016-10-22T03:09:45", 
    "direction": "Flat", 
    "sgv": 97, 
    "display_time": "2016-10-21T20:10:07", 
    "date": 1477105807000.0, 
    "dateString": "2016-10-21T20:10:07", 
    "device": "openaps://cgm", 
    "type": "sgv", 
    "glucose": 97
  }, 
  {
    "trend_arrow": "FLAT", 
    "system_time": "2016-10-22T03:04:48", 
    "direction": "Flat", 
    "sgv": 100, 
    "display_time": "2016-10-21T20:05:10", 
    "date": 1477105510000.0, 
    "dateString": "2016-10-21T20:05:10", 
    "device": "openaps://cgm", 
    "type": "sgv", 
    "glucose": 100
  }, 
  {
    "trend_arrow": "FLAT", 
    "system_time": "2016-10-22T02:59:46", 
    "direction": "Flat", 
    "sgv": 105, 
    "display_time": "2016-10-21T20:00:08", 
    "date": 1477105208000.0, 
    "dateString": "2016-10-21T20:00:08", 
    "device": "openaps://cgm", 
    "type": "sgv", 
    "glucose": 105
  }, 
  {
    "trend_arrow": "FLAT", 
    "system_time": "2016-10-22T02:54:46", 
    "direction": "Flat", 
    "sgv": 109, 
    "display_time": "2016-10-21T19:55:08", 
    "date": 1477104908000.0, 
    "dateString": "2016-10-21T19:55:08", 
    "device": "openaps://cgm", 
    "type": "sgv", 
    "glucose": 109
  }, 
  {
    "trend_arrow": "45_DOWN", 
    "system_time": "2016-10-22T02:49:47", 
    "direction": "FortyFiveDown", 
    "sgv": 112, 
    "display_time": "2016-10-21T19:50:10", 
    "date": 1477104610000.0, 
    "dateString": "2016-10-21T19:50:10", 
    "device": "openaps://cgm", 
    "type": "sgv", 
    "glucose": 112
  }, 
  {
    "trend_arrow": "45_DOWN", 
    "system_time": "2016-10-22T02:44:44", 
    "direction": "FortyFiveDown", 
    "sgv": 116, 
    "display_time": "2016-10-21T19:45:07", 
    "date": 1477104307000.0, 
    "dateString": "2016-10-21T19:45:07", 
    "device": "openaps://cgm", 
    "type": "sgv", 
    "glucose": 116
  }, 
  {
    "trend_arrow": "45_DOWN", 
    "system_time": "2016-10-22T02:39:52", 
    "direction": "FortyFiveDown", 
    "sgv": 121, 
    "display_time": "2016-10-21T19:40:15", 
    "date": 1477104015000.0, 
    "dateString": "2016-10-21T19:40:15", 
    "device": "openaps://cgm", 
    "type": "sgv", 
    "glucose": 121
  }, 
  {
    "trend_arrow": "45_DOWN", 
    "system_time": "2016-10-22T02:34:46", 
    "direction": "FortyFiveDown", 
    "sgv": 127, 
    "display_time": "2016-10-21T19:35:08", 
    "date": 1477103708000.0, 
    "dateString": "2016-10-21T19:35:08", 
    "device": "openaps://cgm", 
    "type": "sgv", 
    "glucose": 127
  }, 
  {
    "trend_arrow": "45_DOWN", 
    "system_time": "2016-10-22T02:29:50", 
    "direction": "FortyFiveDown", 
    "sgv": 136, 
    "display_time": "2016-10-21T19:30:12", 
    "date": 1477103412000.0, 
    "dateString": "2016-10-21T19:30:12", 
    "device": "openaps://cgm", 
    "type": "sgv", 
    "glucose": 136
  }, 
  {
    "trend_arrow": "SINGLE_DOWN", 
    "system_time": "2016-10-22T02:25:01", 
    "direction": "SingleDown", 
    "sgv": 142, 
    "display_time": "2016-10-21T19:25:23", 
    "date": 1477103123000.0, 
    "dateString": "2016-10-21T19:25:23", 
    "device": "openaps://cgm", 
    "type": "sgv", 
    "glucose": 142
  }, 
  {
    "trend_arrow": "45_DOWN", 
    "system_time": "2016-10-22T02:19:50", 
    "direction": "FortyFiveDown", 
    "sgv": 151, 
    "display_time": "2016-10-21T19:20:13", 
    "date": 1477102813000.0, 
    "dateString": "2016-10-21T19:20:13", 
    "device": "openaps://cgm", 
    "type": "sgv", 
    "glucose": 151
  }, 
  {
    "trend_arrow": "45_DOWN", 
    "system_time": "2016-10-22T02:14:47", 
    "direction": "FortyFiveDown", 
    "sgv": 162, 
    "display_time": "2016-10-21T19:15:09", 
    "date": 1477102509000.0, 
    "dateString": "2016-10-21T19:15:09", 
    "device": "openaps://cgm", 
    "type": "sgv", 
    "glucose": 162
  }, 
  {
    "trend_arrow": "45_DOWN", 
    "system_time": "2016-10-22T02:09:53", 
    "direction": "FortyFiveDown", 
    "sgv": 171, 
    "display_time": "2016-10-21T19:10:16", 
    "date": 1477102216000.0, 
    "dateString": "2016-10-21T19:10:16", 
    "device": "openaps://cgm", 
    "type": "sgv", 
    "glucose": 171
  }, 
  {
    "trend_arrow": "FLAT", 
    "system_time": "2016-10-22T01:59:51", 
    "direction": "Flat", 
    "sgv": 183, 
    "display_time": "2016-10-21T19:00:14", 
    "date": 1477101614000.0, 
    "dateString": "2016-10-21T19:00:14", 
    "device": "openaps://cgm", 
    "type": "sgv", 
    "glucose": 183
  }, 
  {
    "trend_arrow": "FLAT", 
    "system_time": "2016-10-22T01:54:52", 
    "direction": "Flat", 
    "sgv": 185, 
    "display_time": "2016-10-21T18:55:14", 
    "date": 1477101314000.0, 
    "dateString": "2016-10-21T18:55:14", 
    "device": "openaps://cgm", 
    "type": "sgv", 
    "glucose": 185
  }, 
  {
    "trend_arrow": "45_DOWN", 
    "system_time": "2016-10-22T01:29:46", 
    "direction": "FortyFiveDown", 
    "sgv": 215, 
    "display_time": "2016-10-21T18:30:09", 
    "date": 1477099809000.0, 
    "dateString": "2016-10-21T18:30:09", 
    "device": "openaps://cgm", 
    "type": "sgv", 
    "glucose": 215
  }, 
  {
    "trend_arrow": "45_DOWN", 
    "system_time": "2016-10-22T01:24:47", 
    "direction": "FortyFiveDown", 
    "sgv": 223, 
    "display_time": "2016-10-21T18:25:10", 
    "date": 1477099510000.0, 
    "dateString": "2016-10-21T18:25:10", 
    "device": "openaps://cgm", 
    "type": "sgv", 
    "glucose": 223
  }, 
  {
    "trend_arrow": "45_DOWN", 
    "system_time": "2016-10-22T01:19:57", 
    "direction": "FortyFiveDown", 
    "sgv": 233, 
    "display_time": "2016-10-21T18:20:19", 
    "date": 1477099219000.0, 
    "dateString": "2016-10-21T18:20:19", 
    "device": "openaps://cgm", 
    "type": "sgv", 
    "glucose": 233
  }, 
  {
    "trend_arrow": "45_DOWN", 
    "system_time": "2016-10-22T01:14:46", 
    "direction": "FortyFiveDown", 
    "sgv": 238, 
    "display_time": "2016-10-21T18:15:08", 
    "date": 1477098908000.0, 
    "dateString": "2016-10-21T18:15:08", 
    "device": "openaps://cgm", 
    "type": "sgv", 
    "glucose": 238
  }, 
  {
    "trend_arrow": "FLAT", 
    "system_time": "2016-10-22T01:09:53", 
    "direction": "Flat", 
    "sgv": 243, 
    "display_time": "2016-10-21T18:10:16", 
    "date": 1477098616000.0, 
    "dateString": "2016-10-21T18:10:16", 
    "device": "openaps://cgm", 
    "type": "sgv", 
    "glucose": 243
  }, 
  {
    "trend_arrow": "FLAT", 
    "system_time": "2016-10-22T01:04:47", 
    "direction": "Flat", 
    "sgv": 247, 
    "display_time": "2016-10-21T18:05:09", 
    "date": 1477098309000.0, 
    "dateString": "2016-10-21T18:05:09", 
    "device": "openaps://cgm", 
    "type": "sgv", 
    "glucose": 247
  }, 
  {
    "trend_arrow": "FLAT", 
    "system_time": "2016-10-22T01:00:02", 
    "direction": "Flat", 
    "sgv": 253, 
    "display_time": "2016-10-21T18:00:24", 
    "date": 1477098024000.0, 
    "dateString": "2016-10-21T18:00:24", 
    "device": "openaps://cgm", 
    "type": "sgv", 
    "glucose": 253
  }, 
  {
    "trend_arrow": "45_DOWN", 
    "system_time": "2016-10-22T00:54:46", 
    "direction": "FortyFiveDown", 
    "sgv": 259, 
    "display_time": "2016-10-21T17:55:08", 
    "date": 1477097708000.0, 
    "dateString": "2016-10-21T17:55:08", 
    "device": "openaps://cgm", 
    "type": "sgv", 
    "glucose": 259
  }, 
  {
    "trend_arrow": "45_DOWN", 
    "system_time": "2016-10-22T00:49:47", 
    "direction": "FortyFiveDown", 
    "sgv": 253, 
    "display_time": "2016-10-21T17:50:10", 
    "date": 1477097410000.0, 
    "dateString": "2016-10-21T17:50:10", 
    "device": "openaps://cgm", 
    "type": "sgv", 
    "glucose": 253
  }, 
  {
    "trend_arrow": "45_DOWN", 
    "system_time": "2016-10-22T00:44:47", 
    "direction": "FortyFiveDown", 
    "sgv": 264, 
    "display_time": "2016-10-21T17:45:09", 
    "date": 1477097109000.0, 
    "dateString": "2016-10-21T17:45:09", 
    "device": "openaps://cgm", 
    "type": "sgv", 
    "glucose": 264
  }, 
  {
    "trend_arrow": "45_DOWN", 
    "system_time": "2016-10-22T00:39:54", 
    "direction": "FortyFiveDown", 
    "sgv": 273, 
    "display_time": "2016-10-21T17:40:16", 
    "date": 1477096816000.0, 
    "dateString": "2016-10-21T17:40:16", 
    "device": "openaps://cgm", 
    "type": "sgv", 
    "glucose": 273
  }, 
  {
    "trend_arrow": "45_DOWN", 
    "system_time": "2016-10-22T00:34:56", 
    "direction": "FortyFiveDown", 
    "sgv": 279, 
    "display_time": "2016-10-21T17:35:18", 
    "date": 1477096518000.0, 
    "dateString": "2016-10-21T17:35:18", 
    "device": "openaps://cgm", 
    "type": "sgv", 
    "glucose": 279
  }, 
  {
    "trend_arrow": "FLAT", 
    "system_time": "2016-10-22T00:24:45", 
    "direction": "Flat", 
    "sgv": 288, 
    "display_time": "2016-10-21T17:25:07", 
    "date": 1477095907000.0, 
    "dateString": "2016-10-21T17:25:07", 
    "device": "openaps://cgm", 
    "type": "sgv", 
    "glucose": 288
  }, 
  {
    "trend_arrow": "FLAT", 
    "system_time": "2016-10-22T00:19:53", 
    "direction": "Flat", 
    "sgv": 293, 
    "display_time": "2016-10-21T17:20:15", 
    "date": 1477095615000.0, 
    "dateString": "2016-10-21T17:20:15", 
    "device": "openaps://cgm", 
    "type": "sgv", 
    "glucose": 293
  }, 
  {
    "trend_arrow": "45_DOWN", 
    "system_time": "2016-10-22T00:09:47", 
    "direction": "FortyFiveDown", 
    "sgv": 301, 
    "display_time": "2016-10-21T17:10:09", 
    "date": 1477095009000.0, 
    "dateString": "2016-10-21T17:10:09", 
    "device": "openaps://cgm", 
    "type": "sgv", 
    "glucose": 301
  }, 
  {
    "trend_arrow": "45_DOWN", 
    "system_time": "2016-10-22T00:04:49", 
    "direction": "FortyFiveDown", 
    "sgv": 305, 
    "display_time": "2016-10-21T17:05:12", 
    "date": 1477094712000.0, 
    "dateString": "2016-10-21T17:05:12", 
    "device": "openaps://cgm", 
    "type": "sgv", 
    "glucose": 305
  }, 
  {
    "trend_arrow": "45_DOWN", 
    "system_time": "2016-10-21T23:59:49", 
    "direction": "FortyFiveDown", 
    "sgv": 311, 
    "display_time": "2016-10-21T17:00:12", 
    "date": 1477094412000.0, 
    "dateString": "2016-10-21T17:00:12", 
    "device": "openaps://cgm", 
    "type": "sgv", 
    "glucose": 311
  }, 
  {
    "trend_arrow": "45_DOWN", 
    "system_time": "2016-10-21T23:50:04", 
    "direction": "FortyFiveDown", 
    "sgv": 327, 
    "display_time": "2016-10-21T16:50:26", 
    "date": 1477093826000.0, 
    "dateString": "2016-10-21T16:50:26", 
    "device": "openaps://cgm", 
    "type": "sgv", 
    "glucose": 327
  }, 
  {
    "trend_arrow": "45_DOWN", 
    "system_time": "2016-10-21T23:44:46", 
    "direction": "FortyFiveDown", 
    "sgv": 338, 
    "display_time": "2016-10-21T16:45:08", 
    "date": 1477093508000.0, 
    "dateString": "2016-10-21T16:45:08", 
    "device": "openaps://cgm", 
    "type": "sgv", 
    "glucose": 338
  }, 
  {
    "trend_arrow": "45_DOWN", 
    "system_time": "2016-10-21T23:39:52", 
    "direction": "FortyFiveDown", 
    "sgv": 345, 
    "display_time": "2016-10-21T16:40:14", 
    "date": 1477093214000.0, 
    "dateString": "2016-10-21T16:40:14", 
    "device": "openaps://cgm", 
    "type": "sgv", 
    "glucose": 345
  }, 
  {
    "trend_arrow": "FLAT", 
    "system_time": "2016-10-21T23:34:46", 
    "direction": "Flat", 
    "sgv": 352, 
    "display_time": "2016-10-21T16:35:08", 
    "date": 1477092908000.0, 
    "dateString": "2016-10-21T16:35:08", 
    "device": "openaps://cgm", 
    "type": "sgv", 
    "glucose": 352
  }, 
  {
    "trend_arrow": "FLAT", 
    "system_time": "2016-10-21T23:29:48", 
    "direction": "Flat", 
    "sgv": 358, 
    "display_time": "2016-10-21T16:30:10", 
    "date": 1477092610000.0, 
    "dateString": "2016-10-21T16:30:10", 
    "device": "openaps://cgm", 
    "type": "sgv", 
    "glucose": 358
  }, 
  {
    "trend_arrow": "45_DOWN", 
    "system_time": "2016-10-21T23:24:46", 
    "direction": "FortyFiveDown", 
    "sgv": 361, 
    "display_time": "2016-10-21T16:25:08", 
    "date": 1477092308000.0, 
    "dateString": "2016-10-21T16:25:08", 
    "device": "openaps://cgm", 
    "type": "sgv", 
    "glucose": 361
  }, 
  {
    "trend_arrow": "45_DOWN", 
    "system_time": "2016-10-21T23:19:46", 
    "direction": "FortyFiveDown", 
    "sgv": 358, 
    "display_time": "2016-10-21T16:20:08", 
    "date": 1477092008000.0, 
    "dateString": "2016-10-21T16:20:08", 
    "device": "openaps://cgm", 
    "type": "sgv", 
    "glucose": 358
  }, 
  {
    "trend_arrow": "45_DOWN", 
    "system_time": "2016-10-21T23:14:47", 
    "direction": "FortyFiveDown", 
    "sgv": 368, 
    "display_time": "2016-10-21T16:15:09", 
    "date": 1477091709000.0, 
    "dateString": "2016-10-21T16:15:09", 
    "device": "openaps://cgm", 
    "type": "sgv", 
    "glucose": 368
  }, 
  {
    "trend_arrow": "45_DOWN", 
    "system_time": "2016-10-21T23:09:46", 
    "direction": "FortyFiveDown", 
    "sgv": 376, 
    "display_time": "2016-10-21T16:10:09", 
    "date": 1477091409000.0, 
    "dateString": "2016-10-21T16:10:09", 
    "device": "openaps://cgm", 
    "type": "sgv", 
    "glucose": 376
  }, 
  {
    "trend_arrow": "45_DOWN", 
    "system_time": "2016-10-21T23:04:47", 
    "direction": "FortyFiveDown", 
    "sgv": 382, 
    "display_time": "2016-10-21T16:05:09", 
    "date": 1477091109000.0, 
    "dateString": "2016-10-21T16:05:09", 
    "device": "openaps://cgm", 
    "type": "sgv", 
    "glucose": 382
  }, 
  {
    "trend_arrow": "FLAT", 
    "system_time": "2016-10-21T22:59:47", 
    "direction": "Flat", 
    "sgv": 392, 
    "display_time": "2016-10-21T16:00:10", 
    "date": 1477090810000.0, 
    "dateString": "2016-10-21T16:00:10", 
    "device": "openaps://cgm", 
    "type": "sgv", 
    "glucose": 392
  }, 
  {
    "trend_arrow": "FLAT", 
    "system_time": "2016-10-21T22:54:50", 
    "direction": "Flat", 
    "sgv": 399, 
    "display_time": "2016-10-21T15:55:13", 
    "date": 1477090513000.0, 
    "dateString": "2016-10-21T15:55:13", 
    "device": "openaps://cgm", 
    "type": "sgv", 
    "glucose": 399
  }, 
  {
    "trend_arrow": "FLAT", 
    "system_time": "2016-10-21T22:49:50", 
    "direction": "Flat", 
    "sgv": 401, 
    "display_time": "2016-10-21T15:50:13", 
    "date": 1477090213000.0, 
    "dateString": "2016-10-21T15:50:13", 
    "device": "openaps://cgm", 
    "type": "sgv", 
    "glucose": 401
  }, 
  {
    "trend_arrow": "FLAT", 
    "system_time": "2016-10-21T22:44:47", 
    "direction": "Flat", 
    "sgv": 401, 
    "display_time": "2016-10-21T15:45:09", 
    "date": 1477089909000.0, 
    "dateString": "2016-10-21T15:45:09", 
    "device": "openaps://cgm", 
    "type": "sgv", 
    "glucose": 401
  }, 
  {
    "trend_arrow": "FLAT", 
    "system_time": "2016-10-21T22:39:45", 
    "direction": "Flat", 
    "sgv": 399, 
    "display_time": "2016-10-21T15:40:08", 
    "date": 1477089608000.0, 
    "dateString": "2016-10-21T15:40:08", 
    "device": "openaps://cgm", 
    "type": "sgv", 
    "glucose": 399
  }, 
  {
    "trend_arrow": "FLAT", 
    "system_time": "2016-10-21T22:34:47", 
    "direction": "Flat", 
    "sgv": 397, 
    "display_time": "2016-10-21T15:35:09", 
    "date": 1477089309000.0, 
    "dateString": "2016-10-21T15:35:09", 
    "device": "openaps://cgm", 
    "type": "sgv", 
    "glucose": 397
  }, 
  {
    "trend_arrow": "45_DOWN", 
    "system_time": "2016-10-21T22:29:47", 
    "direction": "FortyFiveDown", 
    "sgv": 396, 
    "display_time": "2016-10-21T15:30:09", 
    "date": 1477089009000.0, 
    "dateString": "2016-10-21T15:30:09", 
    "device": "openaps://cgm", 
    "type": "sgv", 
    "glucose": 396
  }, 
  {
    "trend_arrow": "45_DOWN", 
    "system_time": "2016-10-21T22:24:48", 
    "direction": "FortyFiveDown", 
    "sgv": 400, 
    "display_time": "2016-10-21T15:25:10", 
    "date": 1477088710000.0, 
    "dateString": "2016-10-21T15:25:10", 
    "device": "openaps://cgm", 
    "type": "sgv", 
    "glucose": 400
  }, 
  {
    "trend_arrow": "45_DOWN", 
    "system_time": "2016-10-21T22:19:45", 
    "direction": "FortyFiveDown", 
    "sgv": 401, 
    "display_time": "2016-10-21T15:20:08", 
    "date": 1477088408000.0, 
    "dateString": "2016-10-21T15:20:08", 
    "device": "openaps://cgm", 
    "type": "sgv", 
    "glucose": 401
  }, 
  {
    "trend_arrow": "45_DOWN", 
    "system_time": "2016-10-21T22:14:48", 
    "direction": "FortyFiveDown", 
    "sgv": 401, 
    "display_time": "2016-10-21T15:15:11", 
    "date": 1477088111000.0, 
    "dateString": "2016-10-21T15:15:11", 
    "device": "openaps://cgm", 
    "type": "sgv", 
    "glucose": 401
  }, 
  {
    "trend_arrow": "45_DOWN", 
    "system_time": "2016-10-21T22:09:50", 
    "direction": "FortyFiveDown", 
    "sgv": 401, 
    "display_time": "2016-10-21T15:10:13", 
    "date": 1477087813000.0, 
    "dateString": "2016-10-21T15:10:13", 
    "device": "openaps://cgm", 
    "type": "sgv", 
    "glucose": 401
  }, 
  {
    "trend_arrow": "FLAT", 
    "system_time": "2016-10-21T22:04:46", 
    "direction": "Flat", 
    "sgv": 401, 
    "display_time": "2016-10-21T15:05:09", 
    "date": 1477087509000.0, 
    "dateString": "2016-10-21T15:05:09", 
    "device": "openaps://cgm", 
    "type": "sgv", 
    "glucose": 401
  }, 
  {
    "trend_arrow": "FLAT", 
    "system_time": "2016-10-21T21:59:45", 
    "direction": "Flat", 
    "sgv": 401, 
    "display_time": "2016-10-21T15:00:08", 
    "date": 1477087208000.0, 
    "dateString": "2016-10-21T15:00:08", 
    "device": "openaps://cgm", 
    "type": "sgv", 
    "glucose": 401
  }, 
  {
    "trend_arrow": "FLAT", 
    "system_time": "2016-10-21T21:54:46", 
    "direction": "Flat", 
    "sgv": 401, 
    "display_time": "2016-10-21T14:55:09", 
    "date": 1477086909000.0, 
    "dateString": "2016-10-21T14:55:09", 
    "device": "openaps://cgm", 
    "type": "sgv", 
    "glucose": 401
  }, 
  {
    "trend_arrow": "FLAT", 
    "system_time": "2016-10-21T21:49:46", 
    "direction": "Flat", 
    "sgv": 401, 
    "display_time": "2016-10-21T14:50:08", 
    "date": 1477086608000.0, 
    "dateString": "2016-10-21T14:50:08", 
    "device": "openaps://cgm", 
    "type": "sgv", 
    "glucose": 401
  }, 
  {
    "trend_arrow": "FLAT", 
    "system_time": "2016-10-21T21:44:47", 
    "direction": "Flat", 
    "sgv": 401, 
    "display_time": "2016-10-21T14:45:09", 
    "date": 1477086309000.0, 
    "dateString": "2016-10-21T14:45:09", 
    "device": "openaps://cgm", 
    "type": "sgv", 
    "glucose": 401
  }, 
  {
    "trend_arrow": "FLAT", 
    "system_time": "2016-10-21T21:39:46", 
    "direction": "Flat", 
    "sgv": 401, 
    "display_time": "2016-10-21T14:40:08", 
    "date": 1477086008000.0, 
    "dateString": "2016-10-21T14:40:08", 
    "device": "openaps://cgm", 
    "type": "sgv", 
    "glucose": 401
  }, 
  {
    "trend_arrow": "FLAT", 
    "system_time": "2016-10-21T21:34:48", 
    "direction": "Flat", 
    "sgv": 401, 
    "display_time": "2016-10-21T14:35:10", 
    "date": 1477085710000.0, 
    "dateString": "2016-10-21T14:35:10", 
    "device": "openaps://cgm", 
    "type": "sgv", 
    "glucose": 401
  }, 
  {
    "trend_arrow": "FLAT", 
    "system_time": "2016-10-21T21:29:46", 
    "direction": "Flat", 
    "sgv": 401, 
    "display_time": "2016-10-21T14:30:09", 
    "date": 1477085409000.0, 
    "dateString": "2016-10-21T14:30:09", 
    "device": "openaps://cgm", 
    "type": "sgv", 
    "glucose": 401
  }, 
  {
    "trend_arrow": "FLAT", 
    "system_time": "2016-10-21T21:24:48", 
    "direction": "Flat", 
    "sgv": 401, 
    "display_time": "2016-10-21T14:25:10", 
    "date": 1477085110000.0, 
    "dateString": "2016-10-21T14:25:10", 
    "device": "openaps://cgm", 
    "type": "sgv", 
    "glucose": 401
  }, 
  {
    "trend_arrow": "FLAT", 
    "system_time": "2016-10-21T21:19:47", 
    "direction": "Flat", 
    "sgv": 401, 
    "display_time": "2016-10-21T14:20:09", 
    "date": 1477084809000.0, 
    "dateString": "2016-10-21T14:20:09", 
    "device": "openaps://cgm", 
    "type": "sgv", 
    "glucose": 401
  }, 
  {
    "trend_arrow": "FLAT", 
    "system_time": "2016-10-21T21:14:49", 
    "direction": "Flat", 
    "sgv": 401, 
    "display_time": "2016-10-21T14:15:11", 
    "date": 1477084511000.0, 
    "dateString": "2016-10-21T14:15:11", 
    "device": "openaps://cgm", 
    "type": "sgv", 
    "glucose": 401
  }, 
  {
    "trend_arrow": "FLAT", 
    "system_time": "2016-10-21T21:09:47", 
    "direction": "Flat", 
    "sgv": 401, 
    "display_time": "2016-10-21T14:10:10", 
    "date": 1477084210000.0, 
    "dateString": "2016-10-21T14:10:10", 
    "device": "openaps://cgm", 
    "type": "sgv", 
    "glucose": 401
  }, 
  {
    "trend_arrow": "FLAT", 
    "system_time": "2016-10-21T21:04:47", 
    "direction": "Flat", 
    "sgv": 401, 
    "display_time": "2016-10-21T14:05:09", 
    "date": 1477083909000.0, 
    "dateString": "2016-10-21T14:05:09", 
    "device": "openaps://cgm", 
    "type": "sgv", 
    "glucose": 401
  }, 
  {
    "trend_arrow": "45_UP", 
    "system_time": "2016-10-21T20:54:53", 
    "direction": "FortyFiveUp", 
    "sgv": 401, 
    "display_time": "2016-10-21T13:55:16", 
    "date": 1477083316000.0, 
    "dateString": "2016-10-21T13:55:16", 
    "device": "openaps://cgm", 
    "type": "sgv", 
    "glucose": 401
  }, 
  {
    "trend_arrow": "45_UP", 
    "system_time": "2016-10-21T20:49:49", 
    "direction": "FortyFiveUp", 
    "sgv": 401, 
    "display_time": "2016-10-21T13:50:12", 
    "date": 1477083012000.0, 
    "dateString": "2016-10-21T13:50:12", 
    "device": "openaps://cgm", 
    "type": "sgv", 
    "glucose": 401
  }, 
  {
    "trend_arrow": "FLAT", 
    "system_time": "2016-10-21T20:45:02", 
    "direction": "Flat", 
    "sgv": 401, 
    "display_time": "2016-10-21T13:45:25", 
    "date": 1477082725000.0, 
    "dateString": "2016-10-21T13:45:25", 
    "device": "openaps://cgm", 
    "type": "sgv", 
    "glucose": 401
  }, 
  {
    "trend_arrow": "FLAT", 
    "system_time": "2016-10-21T19:04:47", 
    "direction": "Flat", 
    "sgv": 45, 
    "display_time": "2016-10-21T12:05:10", 
    "date": 1477076710000.0, 
    "dateString": "2016-10-21T12:05:10", 
    "device": "openaps://cgm", 
    "type": "sgv", 
    "glucose": 45
  }, 
  {
    "trend_arrow": "45_DOWN", 
    "system_time": "2016-10-21T18:59:47", 
    "direction": "FortyFiveDown", 
    "sgv": 47, 
    "display_time": "2016-10-21T12:00:10", 
    "date": 1477076410000.0, 
    "dateString": "2016-10-21T12:00:10", 
    "device": "openaps://cgm", 
    "type": "sgv", 
    "glucose": 47
  }, 
  {
    "trend_arrow": "45_DOWN", 
    "system_time": "2016-10-21T18:54:50", 
    "direction": "FortyFiveDown", 
    "sgv": 51, 
    "display_time": "2016-10-21T11:55:12", 
    "date": 1477076112000.0, 
    "dateString": "2016-10-21T11:55:12", 
    "device": "openaps://cgm", 
    "type": "sgv", 
    "glucose": 51
  }, 
  {
    "trend_arrow": "45_DOWN", 
    "system_time": "2016-10-21T18:49:45", 
    "direction": "FortyFiveDown", 
    "sgv": 48, 
    "display_time": "2016-10-21T11:50:07", 
    "date": 1477075807000.0, 
    "dateString": "2016-10-21T11:50:07", 
    "device": "openaps://cgm", 
    "type": "sgv", 
    "glucose": 48
  }, 
  {
    "trend_arrow": "45_DOWN", 
    "system_time": "2016-10-21T18:44:49", 
    "direction": "FortyFiveDown", 
    "sgv": 54, 
    "display_time": "2016-10-21T11:45:11", 
    "date": 1477075511000.0, 
    "dateString": "2016-10-21T11:45:11", 
    "device": "openaps://cgm", 
    "type": "sgv", 
    "glucose": 54
  }, 
  {
    "trend_arrow": "45_DOWN", 
    "system_time": "2016-10-21T18:39:44", 
    "direction": "FortyFiveDown", 
    "sgv": 60, 
    "display_time": "2016-10-21T11:40:07", 
    "date": 1477075207000.0, 
    "dateString": "2016-10-21T11:40:07", 
    "device": "openaps://cgm", 
    "type": "sgv", 
    "glucose": 60
  }, 
  {
    "trend_arrow": "45_DOWN", 
    "system_time": "2016-10-21T18:34:44", 
    "direction": "FortyFiveDown", 
    "sgv": 66, 
    "display_time": "2016-10-21T11:35:07", 
    "date": 1477074907000.0, 
    "dateString": "2016-10-21T11:35:07", 
    "device": "openaps://cgm", 
    "type": "sgv", 
    "glucose": 66
  }, 
  {
    "trend_arrow": "45_DOWN", 
    "system_time": "2016-10-21T18:29:54", 
    "direction": "FortyFiveDown", 
    "sgv": 73, 
    "display_time": "2016-10-21T11:30:16", 
    "date": 1477074616000.0, 
    "dateString": "2016-10-21T11:30:16", 
    "device": "openaps://cgm", 
    "type": "sgv", 
    "glucose": 73
  }, 
  {
    "trend_arrow": "45_DOWN", 
    "system_time": "2016-10-21T18:24:49", 
    "direction": "FortyFiveDown", 
    "sgv": 82, 
    "display_time": "2016-10-21T11:25:12", 
    "date": 1477074312000.0, 
    "dateString": "2016-10-21T11:25:12", 
    "device": "openaps://cgm", 
    "type": "sgv", 
    "glucose": 82
  }, 
  {
    "trend_arrow": "45_DOWN", 
    "system_time": "2016-10-21T18:19:44", 
    "direction": "FortyFiveDown", 
    "sgv": 90, 
    "display_time": "2016-10-21T11:20:07", 
    "date": 1477074007000.0, 
    "dateString": "2016-10-21T11:20:07", 
    "device": "openaps://cgm", 
    "type": "sgv", 
    "glucose": 90
  }, 
  {
    "trend_arrow": "45_DOWN", 
    "system_time": "2016-10-21T18:14:45", 
    "direction": "FortyFiveDown", 
    "sgv": 95, 
    "display_time": "2016-10-21T11:15:08", 
    "date": 1477073708000.0, 
    "dateString": "2016-10-21T11:15:08", 
    "device": "openaps://cgm", 
    "type": "sgv", 
    "glucose": 95
  }, 
  {
    "trend_arrow": "45_DOWN", 
    "system_time": "2016-10-21T18:09:57", 
    "direction": "FortyFiveDown", 
    "sgv": 98, 
    "display_time": "2016-10-21T11:10:20", 
    "date": 1477073420000.0, 
    "dateString": "2016-10-21T11:10:20", 
    "device": "openaps://cgm", 
    "type": "sgv", 
    "glucose": 98
  }, 
  {
    "trend_arrow": "45_DOWN", 
    "system_time": "2016-10-21T18:04:51", 
    "direction": "FortyFiveDown", 
    "sgv": 104, 
    "display_time": "2016-10-21T11:05:13", 
    "date": 1477073113000.0, 
    "dateString": "2016-10-21T11:05:13", 
    "device": "openaps://cgm", 
    "type": "sgv", 
    "glucose": 104
  }, 
  {
    "trend_arrow": "45_DOWN", 
    "system_time": "2016-10-21T17:59:49", 
    "direction": "FortyFiveDown", 
    "sgv": 109, 
    "display_time": "2016-10-21T11:00:12", 
    "date": 1477072812000.0, 
    "dateString": "2016-10-21T11:00:12", 
    "device": "openaps://cgm", 
    "type": "sgv", 
    "glucose": 109
  }, 
  {
    "trend_arrow": "45_DOWN", 
    "system_time": "2016-10-21T17:54:45", 
    "direction": "FortyFiveDown", 
    "sgv": 115, 
    "display_time": "2016-10-21T10:55:07", 
    "date": 1477072507000.0, 
    "dateString": "2016-10-21T10:55:07", 
    "device": "openaps://cgm", 
    "type": "sgv", 
    "glucose": 115
  }, 
  {
    "trend_arrow": "45_DOWN", 
    "system_time": "2016-10-21T17:49:45", 
    "direction": "FortyFiveDown", 
    "sgv": 120, 
    "display_time": "2016-10-21T10:50:08", 
    "date": 1477072208000.0, 
    "dateString": "2016-10-21T10:50:08", 
    "device": "openaps://cgm", 
    "type": "sgv", 
    "glucose": 120
  }, 
  {
    "trend_arrow": "45_DOWN", 
    "system_time": "2016-10-21T17:44:47", 
    "direction": "FortyFiveDown", 
    "sgv": 124, 
    "display_time": "2016-10-21T10:45:10", 
    "date": 1477071910000.0, 
    "dateString": "2016-10-21T10:45:10", 
    "device": "openaps://cgm", 
    "type": "sgv", 
    "glucose": 124
  }, 
  {
    "trend_arrow": "45_DOWN", 
    "system_time": "2016-10-21T17:39:45", 
    "direction": "FortyFiveDown", 
    "sgv": 129, 
    "display_time": "2016-10-21T10:40:07", 
    "date": 1477071607000.0, 
    "dateString": "2016-10-21T10:40:07", 
    "device": "openaps://cgm", 
    "type": "sgv", 
    "glucose": 129
  }, 
  {
    "trend_arrow": "SINGLE_DOWN", 
    "system_time": "2016-10-21T17:34:49", 
    "direction": "SingleDown", 
    "sgv": 135, 
    "display_time": "2016-10-21T10:35:11", 
    "date": 1477071311000.0, 
    "dateString": "2016-10-21T10:35:11", 
    "device": "openaps://cgm", 
    "type": "sgv", 
    "glucose": 135
  }, 
  {
    "trend_arrow": "SINGLE_DOWN", 
    "system_time": "2016-10-21T17:29:46", 
    "direction": "SingleDown", 
    "sgv": 143, 
    "display_time": "2016-10-21T10:30:08", 
    "date": 1477071008000.0, 
    "dateString": "2016-10-21T10:30:08", 
    "device": "openaps://cgm", 
    "type": "sgv", 
    "glucose": 143
  }, 
  {
    "trend_arrow": "SINGLE_DOWN", 
    "system_time": "2016-10-21T17:24:45", 
    "direction": "SingleDown", 
    "sgv": 154, 
    "display_time": "2016-10-21T10:25:07", 
    "date": 1477070707000.0, 
    "dateString": "2016-10-21T10:25:07", 
    "device": "openaps://cgm", 
    "type": "sgv", 
    "glucose": 154
  }, 
  {
    "trend_arrow": "SINGLE_DOWN", 
    "system_time": "2016-10-21T17:19:46", 
    "direction": "SingleDown", 
    "sgv": 164, 
    "display_time": "2016-10-21T10:20:08", 
    "date": 1477070408000.0, 
    "dateString": "2016-10-21T10:20:08", 
    "device": "openaps://cgm", 
    "type": "sgv", 
    "glucose": 164
  }, 
  {
    "trend_arrow": "SINGLE_DOWN", 
    "system_time": "2016-10-21T17:14:45", 
    "direction": "SingleDown", 
    "sgv": 176, 
    "display_time": "2016-10-21T10:15:07", 
    "date": 1477070107000.0, 
    "dateString": "2016-10-21T10:15:07", 
    "device": "openaps://cgm", 
    "type": "sgv", 
    "glucose": 176
  }, 
  {
    "trend_arrow": "SINGLE_DOWN", 
    "system_time": "2016-10-21T17:09:46", 
    "direction": "SingleDown", 
    "sgv": 188, 
    "display_time": "2016-10-21T10:10:09", 
    "date": 1477069809000.0, 
    "dateString": "2016-10-21T10:10:09", 
    "device": "openaps://cgm", 
    "type": "sgv", 
    "glucose": 188
  }, 
  {
    "trend_arrow": "45_DOWN", 
    "system_time": "2016-10-21T17:04:45", 
    "direction": "FortyFiveDown", 
    "sgv": 199, 
    "display_time": "2016-10-21T10:05:07", 
    "date": 1477069507000.0, 
    "dateString": "2016-10-21T10:05:07", 
    "device": "openaps://cgm", 
    "type": "sgv", 
    "glucose": 199
  }, 
  {
    "trend_arrow": "FLAT", 
    "system_time": "2016-10-21T16:59:45", 
    "direction": "Flat", 
    "sgv": 209, 
    "display_time": "2016-10-21T10:00:07", 
    "date": 1477069207000.0, 
    "dateString": "2016-10-21T10:00:07", 
    "device": "openaps://cgm", 
    "type": "sgv", 
    "glucose": 209
  }, 
  {
    "trend_arrow": "FLAT", 
    "system_time": "2016-10-21T16:54:45", 
    "direction": "Flat", 
    "sgv": 218, 
    "display_time": "2016-10-21T09:55:08", 
    "date": 1477068908000.0, 
    "dateString": "2016-10-21T09:55:08", 
    "device": "openaps://cgm", 
    "type": "sgv", 
    "glucose": 218
  }, 
  {
    "trend_arrow": "45_UP", 
    "system_time": "2016-10-21T16:49:49", 
    "direction": "FortyFiveUp", 
    "sgv": 223, 
    "display_time": "2016-10-21T09:50:12", 
    "date": 1477068612000.0, 
    "dateString": "2016-10-21T09:50:12", 
    "device": "openaps://cgm", 
    "type": "sgv", 
    "glucose": 223
  }, 
  {
    "trend_arrow": "SINGLE_UP", 
    "system_time": "2016-10-21T16:44:49", 
    "direction": "SingleUp", 
    "sgv": 222, 
    "display_time": "2016-10-21T09:45:11", 
    "date": 1477068311000.0, 
    "dateString": "2016-10-21T09:45:11", 
    "device": "openaps://cgm", 
    "type": "sgv", 
    "glucose": 222
  }, 
  {
    "trend_arrow": "DOUBLE_UP", 
    "system_time": "2016-10-21T16:39:45", 
    "direction": "DoubleUp", 
    "sgv": 218, 
    "display_time": "2016-10-21T09:40:07", 
    "date": 1477068007000.0, 
    "dateString": "2016-10-21T09:40:07", 
    "device": "openaps://cgm", 
    "type": "sgv", 
    "glucose": 218
  }, 
  {
    "trend_arrow": "DOUBLE_UP", 
    "system_time": "2016-10-21T16:34:45", 
    "direction": "DoubleUp", 
    "sgv": 208, 
    "display_time": "2016-10-21T09:35:08", 
    "date": 1477067708000.0, 
    "dateString": "2016-10-21T09:35:08", 
    "device": "openaps://cgm", 
    "type": "sgv", 
    "glucose": 208
  }, 
  {
    "trend_arrow": "DOUBLE_UP", 
    "system_time": "2016-10-21T16:29:45", 
    "direction": "DoubleUp", 
    "sgv": 194, 
    "display_time": "2016-10-21T09:30:07", 
    "date": 1477067407000.0, 
    "dateString": "2016-10-21T09:30:07", 
    "device": "openaps://cgm", 
    "type": "sgv", 
    "glucose": 194
  }, 
  {
    "trend_arrow": "SINGLE_UP", 
    "system_time": "2016-10-21T16:24:45", 
    "direction": "SingleUp", 
    "sgv": 178, 
    "display_time": "2016-10-21T09:25:07", 
    "date": 1477067107000.0, 
    "dateString": "2016-10-21T09:25:07", 
    "device": "openaps://cgm", 
    "type": "sgv", 
    "glucose": 178
  }, 
  {
    "trend_arrow": "SINGLE_UP", 
    "system_time": "2016-10-21T16:19:45", 
    "direction": "SingleUp", 
    "sgv": 161, 
    "display_time": "2016-10-21T09:20:07", 
    "date": 1477066807000.0, 
    "dateString": "2016-10-21T09:20:07", 
    "device": "openaps://cgm", 
    "type": "sgv", 
    "glucose": 161
  }, 
  {
    "trend_arrow": "45_UP", 
    "system_time": "2016-10-21T16:14:45", 
    "direction": "FortyFiveUp", 
    "sgv": 148, 
    "display_time": "2016-10-21T09:15:07", 
    "date": 1477066507000.0, 
    "dateString": "2016-10-21T09:15:07", 
    "device": "openaps://cgm", 
    "type": "sgv", 
    "glucose": 148
  }, 
  {
    "trend_arrow": "FLAT", 
    "system_time": "2016-10-21T16:09:45", 
    "direction": "Flat", 
    "sgv": 136, 
    "display_time": "2016-10-21T09:10:08", 
    "date": 1477066208000.0, 
    "dateString": "2016-10-21T09:10:08", 
    "device": "openaps://cgm", 
    "type": "sgv", 
    "glucose": 136
  }, 
  {
    "trend_arrow": "FLAT", 
    "system_time": "2016-10-21T16:04:45", 
    "direction": "Flat", 
    "sgv": 133, 
    "display_time": "2016-10-21T09:05:08", 
    "date": 1477065908000.0, 
    "dateString": "2016-10-21T09:05:08", 
    "device": "openaps://cgm", 
    "type": "sgv", 
    "glucose": 133
  }, 
  {
    "trend_arrow": "FLAT", 
    "system_time": "2016-10-21T15:59:45", 
    "direction": "Flat", 
    "sgv": 134, 
    "display_time": "2016-10-21T09:00:07", 
    "date": 1477065607000.0, 
    "dateString": "2016-10-21T09:00:07", 
    "device": "openaps://cgm", 
    "type": "sgv", 
    "glucose": 134
  }, 
  {
    "trend_arrow": "FLAT", 
    "system_time": "2016-10-21T15:54:50", 
    "direction": "Flat", 
    "sgv": 135, 
    "display_time": "2016-10-21T08:55:12", 
    "date": 1477065312000.0, 
    "dateString": "2016-10-21T08:55:12", 
    "device": "openaps://cgm", 
    "type": "sgv", 
    "glucose": 135
  }, 
  {
    "trend_arrow": "FLAT", 
    "system_time": "2016-10-21T15:49:45", 
    "direction": "Flat", 
    "sgv": 139, 
    "display_time": "2016-10-21T08:50:08", 
    "date": 1477065008000.0, 
    "dateString": "2016-10-21T08:50:08", 
    "device": "openaps://cgm", 
    "type": "sgv", 
    "glucose": 139
  }, 
  {
    "trend_arrow": "FLAT", 
    "system_time": "2016-10-21T15:44:46", 
    "direction": "Flat", 
    "sgv": 142, 
    "display_time": "2016-10-21T08:45:08", 
    "date": 1477064708000.0, 
    "dateString": "2016-10-21T08:45:08", 
    "device": "openaps://cgm", 
    "type": "sgv", 
    "glucose": 142
  }, 
  {
    "trend_arrow": "FLAT", 
    "system_time": "2016-10-21T15:39:45", 
    "direction": "Flat", 
    "sgv": 143, 
    "display_time": "2016-10-21T08:40:08", 
    "date": 1477064408000.0, 
    "dateString": "2016-10-21T08:40:08", 
    "device": "openaps://cgm", 
    "type": "sgv", 
    "glucose": 143
  }, 
  {
    "trend_arrow": "45_UP", 
    "system_time": "2016-10-21T15:34:46", 
    "direction": "FortyFiveUp", 
    "sgv": 142, 
    "display_time": "2016-10-21T08:35:08", 
    "date": 1477064108000.0, 
    "dateString": "2016-10-21T08:35:08", 
    "device": "openaps://cgm", 
    "type": "sgv", 
    "glucose": 142
  }, 
  {
    "trend_arrow": "45_UP", 
    "system_time": "2016-10-21T15:29:45", 
    "direction": "FortyFiveUp", 
    "sgv": 140, 
    "display_time": "2016-10-21T08:30:07", 
    "date": 1477063807000.0, 
    "dateString": "2016-10-21T08:30:07", 
    "device": "openaps://cgm", 
    "type": "sgv", 
    "glucose": 140
  }, 
  {
    "trend_arrow": "SINGLE_UP", 
    "system_time": "2016-10-21T15:24:45", 
    "direction": "SingleUp", 
    "sgv": 134, 
    "display_time": "2016-10-21T08:25:08", 
    "date": 1477063508000.0, 
    "dateString": "2016-10-21T08:25:08", 
    "device": "openaps://cgm", 
    "type": "sgv", 
    "glucose": 134
  }, 
  {
    "trend_arrow": "45_UP", 
    "system_time": "2016-10-21T15:09:45", 
    "direction": "FortyFiveUp", 
    "sgv": 107, 
    "display_time": "2016-10-21T08:10:08", 
    "date": 1477062608000.0, 
    "dateString": "2016-10-21T08:10:08", 
    "device": "openaps://cgm", 
    "type": "sgv", 
    "glucose": 107
  }, 
  {
    "trend_arrow": "FLAT", 
    "system_time": "2016-10-21T15:04:45", 
    "direction": "Flat", 
    "sgv": 97, 
    "display_time": "2016-10-21T08:05:08", 
    "date": 1477062308000.0, 
    "dateString": "2016-10-21T08:05:08", 
    "device": "openaps://cgm", 
    "type": "sgv", 
    "glucose": 97
  }, 
  {
    "trend_arrow": "FLAT", 
    "system_time": "2016-10-21T14:59:45", 
    "direction": "Flat", 
    "sgv": 94, 
    "display_time": "2016-10-21T08:00:08", 
    "date": 1477062008000.0, 
    "dateString": "2016-10-21T08:00:08", 
    "device": "openaps://cgm", 
    "type": "sgv", 
    "glucose": 94
  }, 
  {
    "trend_arrow": "FLAT", 
    "system_time": "2016-10-21T14:55:05", 
    "direction": "Flat", 
    "sgv": 92, 
    "display_time": "2016-10-21T07:55:28", 
    "date": 1477061728000.0, 
    "dateString": "2016-10-21T07:55:28", 
    "device": "openaps://cgm", 
    "type": "sgv", 
    "glucose": 92
  }, 
  {
    "trend_arrow": "FLAT", 
    "system_time": "2016-10-21T14:50:05", 
    "direction": "Flat", 
    "sgv": 91, 
    "display_time": "2016-10-21T07:50:28", 
    "date": 1477061428000.0, 
    "dateString": "2016-10-21T07:50:28", 
    "device": "openaps://cgm", 
    "type": "sgv", 
    "glucose": 91
  }, 
  {
    "trend_arrow": "FLAT", 
    "system_time": "2016-10-21T14:44:50", 
    "direction": "Flat", 
    "sgv": 87, 
    "display_time": "2016-10-21T07:45:13", 
    "date": 1477061113000.0, 
    "dateString": "2016-10-21T07:45:13", 
    "device": "openaps://cgm", 
    "type": "sgv", 
    "glucose": 87
  }, 
  {
    "trend_arrow": "FLAT", 
    "system_time": "2016-10-21T14:39:50", 
    "direction": "Flat", 
    "sgv": 87, 
    "display_time": "2016-10-21T07:40:13", 
    "date": 1477060813000.0, 
    "dateString": "2016-10-21T07:40:13", 
    "device": "openaps://cgm", 
    "type": "sgv", 
    "glucose": 87
  }, 
  {
    "trend_arrow": "FLAT", 
    "system_time": "2016-10-21T14:34:47", 
    "direction": "Flat", 
    "sgv": 84, 
    "display_time": "2016-10-21T07:35:10", 
    "date": 1477060510000.0, 
    "dateString": "2016-10-21T07:35:10", 
    "device": "openaps://cgm", 
    "type": "sgv", 
    "glucose": 84
  }, 
  {
    "trend_arrow": "FLAT", 
    "system_time": "2016-10-21T14:29:49", 
    "direction": "Flat", 
    "sgv": 83, 
    "display_time": "2016-10-21T07:30:12", 
    "date": 1477060212000.0, 
    "dateString": "2016-10-21T07:30:12", 
    "device": "openaps://cgm", 
    "type": "sgv", 
    "glucose": 83
  }, 
  {
    "trend_arrow": "FLAT", 
    "system_time": "2016-10-21T14:24:48", 
    "direction": "Flat", 
    "sgv": 94, 
    "display_time": "2016-10-21T07:25:10", 
    "date": 1477059910000.0, 
    "dateString": "2016-10-21T07:25:10", 
    "device": "openaps://cgm", 
    "type": "sgv", 
    "glucose": 94
  }, 
  {
    "trend_arrow": "FLAT", 
    "system_time": "2016-10-21T14:19:49", 
    "direction": "Flat", 
    "sgv": 89, 
    "display_time": "2016-10-21T07:20:11", 
    "date": 1477059611000.0, 
    "dateString": "2016-10-21T07:20:11", 
    "device": "openaps://cgm", 
    "type": "sgv", 
    "glucose": 89
  }, 
  {
    "trend_arrow": "FLAT", 
    "system_time": "2016-10-21T14:14:48", 
    "direction": "Flat", 
    "sgv": 91, 
    "display_time": "2016-10-21T07:15:10", 
    "date": 1477059310000.0, 
    "dateString": "2016-10-21T07:15:10", 
    "device": "openaps://cgm", 
    "type": "sgv", 
    "glucose": 91
  }, 
  {
    "trend_arrow": "FLAT", 
    "system_time": "2016-10-21T14:09:48", 
    "direction": "Flat", 
    "sgv": 95, 
    "display_time": "2016-10-21T07:10:11", 
    "date": 1477059011000.0, 
    "dateString": "2016-10-21T07:10:11", 
    "device": "openaps://cgm", 
    "type": "sgv", 
    "glucose": 95
  }, 
  {
    "trend_arrow": "FLAT", 
    "system_time": "2016-10-21T14:04:48", 
    "direction": "Flat", 
    "sgv": 98, 
    "display_time": "2016-10-21T07:05:10", 
    "date": 1477058710000.0, 
    "dateString": "2016-10-21T07:05:10", 
    "device": "openaps://cgm", 
    "type": "sgv", 
    "glucose": 98
  }, 
  {
    "trend_arrow": "FLAT", 
    "system_time": "2016-10-21T13:59:47", 
    "direction": "Flat", 
    "sgv": 98, 
    "display_time": "2016-10-21T07:00:10", 
    "date": 1477058410000.0, 
    "dateString": "2016-10-21T07:00:10", 
    "device": "openaps://cgm", 
    "type": "sgv", 
    "glucose": 98
  }, 
  {
    "trend_arrow": "FLAT", 
    "system_time": "2016-10-21T13:54:49", 
    "direction": "Flat", 
    "sgv": 100, 
    "display_time": "2016-10-21T06:55:11", 
    "date": 1477058111000.0, 
    "dateString": "2016-10-21T06:55:11", 
    "device": "openaps://cgm", 
    "type": "sgv", 
    "glucose": 100
  }, 
  {
    "trend_arrow": "FLAT", 
    "system_time": "2016-10-21T13:49:47", 
    "direction": "Flat", 
    "sgv": 101, 
    "display_time": "2016-10-21T06:50:10", 
    "date": 1477057810000.0, 
    "dateString": "2016-10-21T06:50:10", 
    "device": "openaps://cgm", 
    "type": "sgv", 
    "glucose": 101
  }, 
  {
    "trend_arrow": "FLAT", 
    "system_time": "2016-10-21T13:44:50", 
    "direction": "Flat", 
    "sgv": 103, 
    "display_time": "2016-10-21T06:45:12", 
    "date": 1477057512000.0, 
    "dateString": "2016-10-21T06:45:12", 
    "device": "openaps://cgm", 
    "type": "sgv", 
    "glucose": 103
  }, 
  {
    "trend_arrow": "FLAT", 
    "system_time": "2016-10-21T13:39:48", 
    "direction": "Flat", 
    "sgv": 103, 
    "display_time": "2016-10-21T06:40:11", 
    "date": 1477057211000.0, 
    "dateString": "2016-10-21T06:40:11", 
    "device": "openaps://cgm", 
    "type": "sgv", 
    "glucose": 103
  }, 
  {
    "trend_arrow": "FLAT", 
    "system_time": "2016-10-21T13:34:48", 
    "direction": "Flat", 
    "sgv": 103, 
    "display_time": "2016-10-21T06:35:11", 
    "date": 1477056911000.0, 
    "dateString": "2016-10-21T06:35:11", 
    "device": "openaps://cgm", 
    "type": "sgv", 
    "glucose": 103
  }, 
  {
    "trend_arrow": "FLAT", 
    "system_time": "2016-10-21T13:29:47", 
    "direction": "Flat", 
    "sgv": 102, 
    "display_time": "2016-10-21T06:30:10", 
    "date": 1477056610000.0, 
    "dateString": "2016-10-21T06:30:10", 
    "device": "openaps://cgm", 
    "type": "sgv", 
    "glucose": 102
  }, 
  {
    "trend_arrow": "FLAT", 
    "system_time": "2016-10-21T13:24:50", 
    "direction": "Flat", 
    "sgv": 104, 
    "display_time": "2016-10-21T06:25:13", 
    "date": 1477056313000.0, 
    "dateString": "2016-10-21T06:25:13", 
    "device": "openaps://cgm", 
    "type": "sgv", 
    "glucose": 104
  }, 
  {
    "trend_arrow": "FLAT", 
    "system_time": "2016-10-21T13:19:50", 
    "direction": "Flat", 
    "sgv": 104, 
    "display_time": "2016-10-21T06:20:12", 
    "date": 1477056012000.0, 
    "dateString": "2016-10-21T06:20:12", 
    "device": "openaps://cgm", 
    "type": "sgv", 
    "glucose": 104
  }, 
  {
    "trend_arrow": "FLAT", 
    "system_time": "2016-10-21T13:14:51", 
    "direction": "Flat", 
    "sgv": 98, 
    "display_time": "2016-10-21T06:15:13", 
    "date": 1477055713000.0, 
    "dateString": "2016-10-21T06:15:13", 
    "device": "openaps://cgm", 
    "type": "sgv", 
    "glucose": 98
  }, 
  {
    "trend_arrow": "FLAT", 
    "system_time": "2016-10-21T13:09:49", 
    "direction": "Flat", 
    "sgv": 96, 
    "display_time": "2016-10-21T06:10:11", 
    "date": 1477055411000.0, 
    "dateString": "2016-10-21T06:10:11", 
    "device": "openaps://cgm", 
    "type": "sgv", 
    "glucose": 96
  }, 
  {
    "trend_arrow": "FLAT", 
    "system_time": "2016-10-21T13:04:48", 
    "direction": "Flat", 
    "sgv": 97, 
    "display_time": "2016-10-21T06:05:10", 
    "date": 1477055110000.0, 
    "dateString": "2016-10-21T06:05:10", 
    "device": "openaps://cgm", 
    "type": "sgv", 
    "glucose": 97
  }, 
  {
    "trend_arrow": "FLAT", 
    "system_time": "2016-10-21T12:59:51", 
    "direction": "Flat", 
    "sgv": 97, 
    "display_time": "2016-10-21T06:00:13", 
    "date": 1477054813000.0, 
    "dateString": "2016-10-21T06:00:13", 
    "device": "openaps://cgm", 
    "type": "sgv", 
    "glucose": 97
  }, 
  {
    "trend_arrow": "FLAT", 
    "system_time": "2016-10-21T12:54:49", 
    "direction": "Flat", 
    "sgv": 99, 
    "display_time": "2016-10-21T05:55:11", 
    "date": 1477054511000.0, 
    "dateString": "2016-10-21T05:55:11", 
    "device": "openaps://cgm", 
    "type": "sgv", 
    "glucose": 99
  }, 
  {
    "trend_arrow": "FLAT", 
    "system_time": "2016-10-21T12:49:51", 
    "direction": "Flat", 
    "sgv": 101, 
    "display_time": "2016-10-21T05:50:14", 
    "date": 1477054214000.0, 
    "dateString": "2016-10-21T05:50:14", 
    "device": "openaps://cgm", 
    "type": "sgv", 
    "glucose": 101
  }, 
  {
    "trend_arrow": "FLAT", 
    "system_time": "2016-10-21T12:44:48", 
    "direction": "Flat", 
    "sgv": 105, 
    "display_time": "2016-10-21T05:45:11", 
    "date": 1477053911000.0, 
    "dateString": "2016-10-21T05:45:11", 
    "device": "openaps://cgm", 
    "type": "sgv", 
    "glucose": 105
  }, 
  {
    "trend_arrow": "FLAT", 
    "system_time": "2016-10-21T12:39:49", 
    "direction": "Flat", 
    "sgv": 107, 
    "display_time": "2016-10-21T05:40:12", 
    "date": 1477053612000.0, 
    "dateString": "2016-10-21T05:40:12", 
    "device": "openaps://cgm", 
    "type": "sgv", 
    "glucose": 107
  }, 
  {
    "trend_arrow": "FLAT", 
    "system_time": "2016-10-21T12:34:49", 
    "direction": "Flat", 
    "sgv": 108, 
    "display_time": "2016-10-21T05:35:11", 
    "date": 1477053311000.0, 
    "dateString": "2016-10-21T05:35:11", 
    "device": "openaps://cgm", 
    "type": "sgv", 
    "glucose": 108
  }, 
  {
    "trend_arrow": "FLAT", 
    "system_time": "2016-10-21T12:29:50", 
    "direction": "Flat", 
    "sgv": 110, 
    "display_time": "2016-10-21T05:30:12", 
    "date": 1477053012000.0, 
    "dateString": "2016-10-21T05:30:12", 
    "device": "openaps://cgm", 
    "type": "sgv", 
    "glucose": 110
  }, 
  {
    "trend_arrow": "FLAT", 
    "system_time": "2016-10-21T12:24:52", 
    "direction": "Flat", 
    "sgv": 116, 
    "display_time": "2016-10-21T05:25:14", 
    "date": 1477052714000.0, 
    "dateString": "2016-10-21T05:25:14", 
    "device": "openaps://cgm", 
    "type": "sgv", 
    "glucose": 116
  }, 
  {
    "trend_arrow": "FLAT", 
    "system_time": "2016-10-21T12:19:48", 
    "direction": "Flat", 
    "sgv": 117, 
    "display_time": "2016-10-21T05:20:11", 
    "date": 1477052411000.0, 
    "dateString": "2016-10-21T05:20:11", 
    "device": "openaps://cgm", 
    "type": "sgv", 
    "glucose": 117
  }, 
  {
    "trend_arrow": "FLAT", 
    "system_time": "2016-10-21T12:14:49", 
    "direction": "Flat", 
    "sgv": 119, 
    "display_time": "2016-10-21T05:15:12", 
    "date": 1477052112000.0, 
    "dateString": "2016-10-21T05:15:12", 
    "device": "openaps://cgm", 
    "type": "sgv", 
    "glucose": 119
  }, 
  {
    "trend_arrow": "FLAT", 
    "system_time": "2016-10-21T12:09:50", 
    "direction": "Flat", 
    "sgv": 123, 
    "display_time": "2016-10-21T05:10:12", 
    "date": 1477051812000.0, 
    "dateString": "2016-10-21T05:10:12", 
    "device": "openaps://cgm", 
    "type": "sgv", 
    "glucose": 123
  }, 
  {
    "trend_arrow": "FLAT", 
    "system_time": "2016-10-21T12:04:49", 
    "direction": "Flat", 
    "sgv": 123, 
    "display_time": "2016-10-21T05:05:11", 
    "date": 1477051511000.0, 
    "dateString": "2016-10-21T05:05:11", 
    "device": "openaps://cgm", 
    "type": "sgv", 
    "glucose": 123
  }, 
  {
    "trend_arrow": "45_DOWN", 
    "system_time": "2016-10-21T11:59:50", 
    "direction": "FortyFiveDown", 
    "sgv": 124, 
    "display_time": "2016-10-21T05:00:12", 
    "date": 1477051212000.0, 
    "dateString": "2016-10-21T05:00:12", 
    "device": "openaps://cgm", 
    "type": "sgv", 
    "glucose": 124
  }, 
  {
    "trend_arrow": "FLAT", 
    "system_time": "2016-10-21T11:54:55", 
    "direction": "Flat", 
    "sgv": 129, 
    "display_time": "2016-10-21T04:55:18", 
    "date": 1477050918000.0, 
    "dateString": "2016-10-21T04:55:18", 
    "device": "openaps://cgm", 
    "type": "sgv", 
    "glucose": 129
  }, 
  {
    "trend_arrow": "FLAT", 
    "system_time": "2016-10-21T11:49:49", 
    "direction": "Flat", 
    "sgv": 137, 
    "display_time": "2016-10-21T04:50:12", 
    "date": 1477050612000.0, 
    "dateString": "2016-10-21T04:50:12", 
    "device": "openaps://cgm", 
    "type": "sgv", 
    "glucose": 137
  }, 
  {
    "trend_arrow": "FLAT", 
    "system_time": "2016-10-21T11:44:50", 
    "direction": "Flat", 
    "sgv": 141, 
    "display_time": "2016-10-21T04:45:12", 
    "date": 1477050312000.0, 
    "dateString": "2016-10-21T04:45:12", 
    "device": "openaps://cgm", 
    "type": "sgv", 
    "glucose": 141
  }, 
  {
    "trend_arrow": "FLAT", 
    "system_time": "2016-10-21T11:39:53", 
    "direction": "Flat", 
    "sgv": 143, 
    "display_time": "2016-10-21T04:40:16", 
    "date": 1477050016000.0, 
    "dateString": "2016-10-21T04:40:16", 
    "device": "openaps://cgm", 
    "type": "sgv", 
    "glucose": 143
  }, 
  {
    "trend_arrow": "FLAT", 
    "system_time": "2016-10-21T11:34:49", 
    "direction": "Flat", 
    "sgv": 143, 
    "display_time": "2016-10-21T04:35:12", 
    "date": 1477049712000.0, 
    "dateString": "2016-10-21T04:35:12", 
    "device": "openaps://cgm", 
    "type": "sgv", 
    "glucose": 143
  }, 
  {
    "trend_arrow": "45_DOWN", 
    "system_time": "2016-10-21T11:29:49", 
    "direction": "FortyFiveDown", 
    "sgv": 143, 
    "display_time": "2016-10-21T04:30:12", 
    "date": 1477049412000.0, 
    "dateString": "2016-10-21T04:30:12", 
    "device": "openaps://cgm", 
    "type": "sgv", 
    "glucose": 143
  }, 
  {
    "trend_arrow": "45_DOWN", 
    "system_time": "2016-10-21T11:24:49", 
    "direction": "FortyFiveDown", 
    "sgv": 148, 
    "display_time": "2016-10-21T04:25:11", 
    "date": 1477049111000.0, 
    "dateString": "2016-10-21T04:25:11", 
    "device": "openaps://cgm", 
    "type": "sgv", 
    "glucose": 148
  }, 
  {
    "trend_arrow": "45_DOWN", 
    "system_time": "2016-10-21T11:19:51", 
    "direction": "FortyFiveDown", 
    "sgv": 153, 
    "display_time": "2016-10-21T04:20:14", 
    "date": 1477048814000.0, 
    "dateString": "2016-10-21T04:20:14", 
    "device": "openaps://cgm", 
    "type": "sgv", 
    "glucose": 153
  }, 
  {
    "trend_arrow": "45_DOWN", 
    "system_time": "2016-10-21T11:14:56", 
    "direction": "FortyFiveDown", 
    "sgv": 165, 
    "display_time": "2016-10-21T04:15:18", 
    "date": 1477048518000.0, 
    "dateString": "2016-10-21T04:15:18", 
    "device": "openaps://cgm", 
    "type": "sgv", 
    "glucose": 165
  }, 
  {
    "trend_arrow": "FLAT", 
    "system_time": "2016-10-21T11:09:48", 
    "direction": "Flat", 
    "sgv": 171, 
    "display_time": "2016-10-21T04:10:11", 
    "date": 1477048211000.0, 
    "dateString": "2016-10-21T04:10:11", 
    "device": "openaps://cgm", 
    "type": "sgv", 
    "glucose": 171
  }, 
  {
    "trend_arrow": "FLAT", 
    "system_time": "2016-10-21T11:04:50", 
    "direction": "Flat", 
    "sgv": 175, 
    "display_time": "2016-10-21T04:05:12", 
    "date": 1477047912000.0, 
    "dateString": "2016-10-21T04:05:12", 
    "device": "openaps://cgm", 
    "type": "sgv", 
    "glucose": 175
  }, 
  {
    "trend_arrow": "FLAT", 
    "system_time": "2016-10-21T10:59:49", 
    "direction": "Flat", 
    "sgv": 180, 
    "display_time": "2016-10-21T04:00:12", 
    "date": 1477047612000.0, 
    "dateString": "2016-10-21T04:00:12", 
    "device": "openaps://cgm", 
    "type": "sgv", 
    "glucose": 180
  }, 
  {
    "trend_arrow": "FLAT", 
    "system_time": "2016-10-21T10:54:48", 
    "direction": "Flat", 
    "sgv": 185, 
    "display_time": "2016-10-21T03:55:11", 
    "date": 1477047311000.0, 
    "dateString": "2016-10-21T03:55:11", 
    "device": "openaps://cgm", 
    "type": "sgv", 
    "glucose": 185
  }, 
  {
    "trend_arrow": "45_DOWN", 
    "system_time": "2016-10-21T10:49:49", 
    "direction": "FortyFiveDown", 
    "sgv": 188, 
    "display_time": "2016-10-21T03:50:12", 
    "date": 1477047012000.0, 
    "dateString": "2016-10-21T03:50:12", 
    "device": "openaps://cgm", 
    "type": "sgv", 
    "glucose": 188
  }, 
  {
    "trend_arrow": "45_DOWN", 
    "system_time": "2016-10-21T10:44:49", 
    "direction": "FortyFiveDown", 
    "sgv": 189, 
    "display_time": "2016-10-21T03:45:11", 
    "date": 1477046711000.0, 
    "dateString": "2016-10-21T03:45:11", 
    "device": "openaps://cgm", 
    "type": "sgv", 
    "glucose": 189
  }, 
  {
    "trend_arrow": "SINGLE_DOWN", 
    "system_time": "2016-10-21T10:39:49", 
    "direction": "SingleDown", 
    "sgv": 192, 
    "display_time": "2016-10-21T03:40:11", 
    "date": 1477046411000.0, 
    "dateString": "2016-10-21T03:40:11", 
    "device": "openaps://cgm", 
    "type": "sgv", 
    "glucose": 192
  }, 
  {
    "trend_arrow": "SINGLE_DOWN", 
    "system_time": "2016-10-21T10:34:50", 
    "direction": "SingleDown", 
    "sgv": 201, 
    "display_time": "2016-10-21T03:35:12", 
    "date": 1477046112000.0, 
    "dateString": "2016-10-21T03:35:12", 
    "device": "openaps://cgm", 
    "type": "sgv", 
    "glucose": 201
  }, 
  {
    "trend_arrow": "SINGLE_DOWN", 
    "system_time": "2016-10-21T10:29:48", 
    "direction": "SingleDown", 
    "sgv": 213, 
    "display_time": "2016-10-21T03:30:10", 
    "date": 1477045810000.0, 
    "dateString": "2016-10-21T03:30:10", 
    "device": "openaps://cgm", 
    "type": "sgv", 
    "glucose": 213
  }, 
  {
    "trend_arrow": "SINGLE_DOWN", 
    "system_time": "2016-10-21T10:24:52", 
    "direction": "SingleDown", 
    "sgv": 220, 
    "display_time": "2016-10-21T03:25:15", 
    "date": 1477045515000.0, 
    "dateString": "2016-10-21T03:25:15", 
    "device": "openaps://cgm", 
    "type": "sgv", 
    "glucose": 220
  }, 
  {
    "trend_arrow": "SINGLE_DOWN", 
    "system_time": "2016-10-21T10:19:49", 
    "direction": "SingleDown", 
    "sgv": 230, 
    "display_time": "2016-10-21T03:20:11", 
    "date": 1477045211000.0, 
    "dateString": "2016-10-21T03:20:11", 
    "device": "openaps://cgm", 
    "type": "sgv", 
    "glucose": 230
  }, 
  {
    "trend_arrow": "SINGLE_DOWN", 
    "system_time": "2016-10-21T10:14:48", 
    "direction": "SingleDown", 
    "sgv": 240, 
    "display_time": "2016-10-21T03:15:11", 
    "date": 1477044911000.0, 
    "dateString": "2016-10-21T03:15:11", 
    "device": "openaps://cgm", 
    "type": "sgv", 
    "glucose": 240
  }, 
  {
    "trend_arrow": "SINGLE_DOWN", 
    "system_time": "2016-10-21T10:09:50", 
    "direction": "SingleDown", 
    "sgv": 255, 
    "display_time": "2016-10-21T03:10:12", 
    "date": 1477044612000.0, 
    "dateString": "2016-10-21T03:10:12", 
    "device": "openaps://cgm", 
    "type": "sgv", 
    "glucose": 255
  }, 
  {
    "trend_arrow": "SINGLE_DOWN", 
    "system_time": "2016-10-21T10:04:49", 
    "direction": "SingleDown", 
    "sgv": 268, 
    "display_time": "2016-10-21T03:05:11", 
    "date": 1477044311000.0, 
    "dateString": "2016-10-21T03:05:11", 
    "device": "openaps://cgm", 
    "type": "sgv", 
    "glucose": 268
  }, 
  {
    "trend_arrow": "SINGLE_DOWN", 
    "system_time": "2016-10-21T09:59:49", 
    "direction": "SingleDown", 
    "sgv": 283, 
    "display_time": "2016-10-21T03:00:12", 
    "date": 1477044012000.0, 
    "dateString": "2016-10-21T03:00:12", 
    "device": "openaps://cgm", 
    "type": "sgv", 
    "glucose": 283
  }, 
  {
    "trend_arrow": "SINGLE_DOWN", 
    "system_time": "2016-10-21T09:54:49", 
    "direction": "SingleDown", 
    "sgv": 293, 
    "display_time": "2016-10-21T02:55:12", 
    "date": 1477043712000.0, 
    "dateString": "2016-10-21T02:55:12", 
    "device": "openaps://cgm", 
    "type": "sgv", 
    "glucose": 293
  }, 
  {
    "trend_arrow": "SINGLE_DOWN", 
    "system_time": "2016-10-21T09:49:48", 
    "direction": "SingleDown", 
    "sgv": 305, 
    "display_time": "2016-10-21T02:50:11", 
    "date": 1477043411000.0, 
    "dateString": "2016-10-21T02:50:11", 
    "device": "openaps://cgm", 
    "type": "sgv", 
    "glucose": 305
  }, 
  {
    "trend_arrow": "SINGLE_DOWN", 
    "system_time": "2016-10-21T09:44:48", 
    "direction": "SingleDown", 
    "sgv": 315, 
    "display_time": "2016-10-21T02:45:10", 
    "date": 1477043110000.0, 
    "dateString": "2016-10-21T02:45:10", 
    "device": "openaps://cgm", 
    "type": "sgv", 
    "glucose": 315
  }, 
  {
    "trend_arrow": "45_DOWN", 
    "system_time": "2016-10-21T09:39:49", 
    "direction": "FortyFiveDown", 
    "sgv": 328, 
    "display_time": "2016-10-21T02:40:11", 
    "date": 1477042811000.0, 
    "dateString": "2016-10-21T02:40:11", 
    "device": "openaps://cgm", 
    "type": "sgv", 
    "glucose": 328
  }, 
  {
    "trend_arrow": "45_DOWN", 
    "system_time": "2016-10-21T09:34:49", 
    "direction": "FortyFiveDown", 
    "sgv": 341, 
    "display_time": "2016-10-21T02:35:12", 
    "date": 1477042512000.0, 
    "dateString": "2016-10-21T02:35:12", 
    "device": "openaps://cgm", 
    "type": "sgv", 
    "glucose": 341
  }, 
  {
    "trend_arrow": "45_DOWN", 
    "system_time": "2016-10-21T09:29:52", 
    "direction": "FortyFiveDown", 
    "sgv": 347, 
    "display_time": "2016-10-21T02:30:15", 
    "date": 1477042215000.0, 
    "dateString": "2016-10-21T02:30:15", 
    "device": "openaps://cgm", 
    "type": "sgv", 
    "glucose": 347
  }, 
  {
    "trend_arrow": "FLAT", 
    "system_time": "2016-10-21T09:24:49", 
    "direction": "Flat", 
    "sgv": 352, 
    "display_time": "2016-10-21T02:25:12", 
    "date": 1477041912000.0, 
    "dateString": "2016-10-21T02:25:12", 
    "device": "openaps://cgm", 
    "type": "sgv", 
    "glucose": 352
  }, 
  {
    "trend_arrow": "FLAT", 
    "system_time": "2016-10-21T09:19:49", 
    "direction": "Flat", 
    "sgv": 357, 
    "display_time": "2016-10-21T02:20:11", 
    "date": 1477041611000.0, 
    "dateString": "2016-10-21T02:20:11", 
    "device": "openaps://cgm", 
    "type": "sgv", 
    "glucose": 357
  }, 
  {
    "trend_arrow": "FLAT", 
    "system_time": "2016-10-21T09:14:49", 
    "direction": "Flat", 
    "sgv": 363, 
    "display_time": "2016-10-21T02:15:11", 
    "date": 1477041311000.0, 
    "dateString": "2016-10-21T02:15:11", 
    "device": "openaps://cgm", 
    "type": "sgv", 
    "glucose": 363
  }, 
  {
    "trend_arrow": "FLAT", 
    "system_time": "2016-10-21T09:09:49", 
    "direction": "Flat", 
    "sgv": 363, 
    "display_time": "2016-10-21T02:10:11", 
    "date": 1477041011000.0, 
    "dateString": "2016-10-21T02:10:11", 
    "device": "openaps://cgm", 
    "type": "sgv", 
    "glucose": 363
  }, 
  {
    "trend_arrow": "FLAT", 
    "system_time": "2016-10-21T09:04:48", 
    "direction": "Flat", 
    "sgv": 361, 
    "display_time": "2016-10-21T02:05:11", 
    "date": 1477040711000.0, 
    "dateString": "2016-10-21T02:05:11", 
    "device": "openaps://cgm", 
    "type": "sgv", 
    "glucose": 361
  }, 
  {
    "trend_arrow": "FLAT", 
    "system_time": "2016-10-21T08:59:50", 
    "direction": "Flat", 
    "sgv": 357, 
    "display_time": "2016-10-21T02:00:12", 
    "date": 1477040412000.0, 
    "dateString": "2016-10-21T02:00:12", 
    "device": "openaps://cgm", 
    "type": "sgv", 
    "glucose": 357
  }, 
  {
    "trend_arrow": "FLAT", 
    "system_time": "2016-10-21T08:54:49", 
    "direction": "Flat", 
    "sgv": 353, 
    "display_time": "2016-10-21T01:55:11", 
    "date": 1477040111000.0, 
    "dateString": "2016-10-21T01:55:11", 
    "device": "openaps://cgm", 
    "type": "sgv", 
    "glucose": 353
  }, 
  {
    "trend_arrow": "FLAT", 
    "system_time": "2016-10-21T08:49:48", 
    "direction": "Flat", 
    "sgv": 351, 
    "display_time": "2016-10-21T01:50:11", 
    "date": 1477039811000.0, 
    "dateString": "2016-10-21T01:50:11", 
    "device": "openaps://cgm", 
    "type": "sgv", 
    "glucose": 351
  }, 
  {
    "trend_arrow": "FLAT", 
    "system_time": "2016-10-21T08:44:49", 
    "direction": "Flat", 
    "sgv": 357, 
    "display_time": "2016-10-21T01:45:12", 
    "date": 1477039512000.0, 
    "dateString": "2016-10-21T01:45:12", 
    "device": "openaps://cgm", 
    "type": "sgv", 
    "glucose": 357
  }, 
  {
    "trend_arrow": "FLAT", 
    "system_time": "2016-10-21T08:39:48", 
    "direction": "Flat", 
    "sgv": 359, 
    "display_time": "2016-10-21T01:40:11", 
    "date": 1477039211000.0, 
    "dateString": "2016-10-21T01:40:11", 
    "device": "openaps://cgm", 
    "type": "sgv", 
    "glucose": 359
  }, 
  {
    "trend_arrow": "FLAT", 
    "system_time": "2016-10-21T08:34:50", 
    "direction": "Flat", 
    "sgv": 358, 
    "display_time": "2016-10-21T01:35:12", 
    "date": 1477038912000.0, 
    "dateString": "2016-10-21T01:35:12", 
    "device": "openaps://cgm", 
    "type": "sgv", 
    "glucose": 358
  }, 
  {
    "trend_arrow": "45_UP", 
    "system_time": "2016-10-21T08:29:48", 
    "direction": "FortyFiveUp", 
    "sgv": 358, 
    "display_time": "2016-10-21T01:30:11", 
    "date": 1477038611000.0, 
    "dateString": "2016-10-21T01:30:11", 
    "device": "openaps://cgm", 
    "type": "sgv", 
    "glucose": 358
  }, 
  {
    "trend_arrow": "SINGLE_UP", 
    "system_time": "2016-10-21T08:24:49", 
    "direction": "SingleUp", 
    "sgv": 356, 
    "display_time": "2016-10-21T01:25:11", 
    "date": 1477038311000.0, 
    "dateString": "2016-10-21T01:25:11", 
    "device": "openaps://cgm", 
    "type": "sgv", 
    "glucose": 356
  }, 
  {
    "trend_arrow": "45_UP", 
    "system_time": "2016-10-21T08:19:51", 
    "direction": "FortyFiveUp", 
    "sgv": 347, 
    "display_time": "2016-10-21T01:20:13", 
    "date": 1477038013000.0, 
    "dateString": "2016-10-21T01:20:13", 
    "device": "openaps://cgm", 
    "type": "sgv", 
    "glucose": 347
  }, 
  {
    "trend_arrow": "45_UP", 
    "system_time": "2016-10-21T08:14:49", 
    "direction": "FortyFiveUp", 
    "sgv": 333, 
    "display_time": "2016-10-21T01:15:11", 
    "date": 1477037711000.0, 
    "dateString": "2016-10-21T01:15:11", 
    "device": "openaps://cgm", 
    "type": "sgv", 
    "glucose": 333
  }, 
  {
    "trend_arrow": "FLAT", 
    "system_time": "2016-10-21T08:09:50", 
    "direction": "Flat", 
    "sgv": 320, 
    "display_time": "2016-10-21T01:10:12", 
    "date": 1477037412000.0, 
    "dateString": "2016-10-21T01:10:12", 
    "device": "openaps://cgm", 
    "type": "sgv", 
    "glucose": 320
  }, 
  {
    "trend_arrow": "FLAT", 
    "system_time": "2016-10-21T08:04:48", 
    "direction": "Flat", 
    "sgv": 316, 
    "display_time": "2016-10-21T01:05:11", 
    "date": 1477037111000.0, 
    "dateString": "2016-10-21T01:05:11", 
    "device": "openaps://cgm", 
    "type": "sgv", 
    "glucose": 316
  }, 
  {
    "trend_arrow": "45_UP", 
    "system_time": "2016-10-21T07:59:51", 
    "direction": "FortyFiveUp", 
    "sgv": 320, 
    "display_time": "2016-10-21T01:00:14", 
    "date": 1477036814000.0, 
    "dateString": "2016-10-21T01:00:14", 
    "device": "openaps://cgm", 
    "type": "sgv", 
    "glucose": 320
  }, 
  {
    "trend_arrow": "45_UP", 
    "system_time": "2016-10-21T07:54:48", 
    "direction": "FortyFiveUp", 
    "sgv": 316, 
    "display_time": "2016-10-21T00:55:11", 
    "date": 1477036511000.0, 
    "dateString": "2016-10-21T00:55:11", 
    "device": "openaps://cgm", 
    "type": "sgv", 
    "glucose": 316
  }, 
  {
    "trend_arrow": "45_UP", 
    "system_time": "2016-10-21T07:49:55", 
    "direction": "FortyFiveUp", 
    "sgv": 307, 
    "display_time": "2016-10-21T00:50:17", 
    "date": 1477036217000.0, 
    "dateString": "2016-10-21T00:50:17", 
    "device": "openaps://cgm", 
    "type": "sgv", 
    "glucose": 307
  }, 
  {
    "trend_arrow": "45_UP", 
    "system_time": "2016-10-21T07:44:49", 
    "direction": "FortyFiveUp", 
    "sgv": 300, 
    "display_time": "2016-10-21T00:45:11", 
    "date": 1477035911000.0, 
    "dateString": "2016-10-21T00:45:11", 
    "device": "openaps://cgm", 
    "type": "sgv", 
    "glucose": 300
  }, 
  {
    "trend_arrow": "45_UP", 
    "system_time": "2016-10-21T07:39:50", 
    "direction": "FortyFiveUp", 
    "sgv": 290, 
    "display_time": "2016-10-21T00:40:13", 
    "date": 1477035613000.0, 
    "dateString": "2016-10-21T00:40:13", 
    "device": "openaps://cgm", 
    "type": "sgv", 
    "glucose": 290
  }, 
  {
    "trend_arrow": "FLAT", 
    "system_time": "2016-10-21T07:34:51", 
    "direction": "Flat", 
    "sgv": 277, 
    "display_time": "2016-10-21T00:35:14", 
    "date": 1477035314000.0, 
    "dateString": "2016-10-21T00:35:14", 
    "device": "openaps://cgm", 
    "type": "sgv", 
    "glucose": 277
  }, 
  {
    "trend_arrow": "FLAT", 
    "system_time": "2016-10-21T07:29:50", 
    "direction": "Flat", 
    "sgv": 275, 
    "display_time": "2016-10-21T00:30:13", 
    "date": 1477035013000.0, 
    "dateString": "2016-10-21T00:30:13", 
    "device": "openaps://cgm", 
    "type": "sgv", 
    "glucose": 275
  }, 
  {
    "trend_arrow": "FLAT", 
    "system_time": "2016-10-21T07:24:49", 
    "direction": "Flat", 
    "sgv": 273, 
    "display_time": "2016-10-21T00:25:12", 
    "date": 1477034712000.0, 
    "dateString": "2016-10-21T00:25:12", 
    "device": "openaps://cgm", 
    "type": "sgv", 
    "glucose": 273
  }, 
  {
    "trend_arrow": "45_DOWN", 
    "system_time": "2016-10-21T07:19:50", 
    "direction": "FortyFiveDown", 
    "sgv": 266, 
    "display_time": "2016-10-21T00:20:12", 
    "date": 1477034412000.0, 
    "dateString": "2016-10-21T00:20:12", 
    "device": "openaps://cgm", 
    "type": "sgv", 
    "glucose": 266
  }, 
  {
    "trend_arrow": "45_DOWN", 
    "system_time": "2016-10-21T07:14:49", 
    "direction": "FortyFiveDown", 
    "sgv": 268, 
    "display_time": "2016-10-21T00:15:12", 
    "date": 1477034112000.0, 
    "dateString": "2016-10-21T00:15:12", 
    "device": "openaps://cgm", 
    "type": "sgv", 
    "glucose": 268
  }, 
  {
    "trend_arrow": "45_DOWN", 
    "system_time": "2016-10-21T07:09:50", 
    "direction": "FortyFiveDown", 
    "sgv": 275, 
    "display_time": "2016-10-21T00:10:12", 
    "date": 1477033812000.0, 
    "dateString": "2016-10-21T00:10:12", 
    "device": "openaps://cgm", 
    "type": "sgv", 
    "glucose": 275
  }, 
  {
    "trend_arrow": "45_DOWN", 
    "system_time": "2016-10-21T07:04:50", 
    "direction": "FortyFiveDown", 
    "sgv": 280, 
    "display_time": "2016-10-21T00:05:13", 
    "date": 1477033513000.0, 
    "dateString": "2016-10-21T00:05:13", 
    "device": "openaps://cgm", 
    "type": "sgv", 
    "glucose": 280
  }, 
  {
    "trend_arrow": "FLAT", 
    "system_time": "2016-10-21T06:59:50", 
    "direction": "Flat", 
    "sgv": 295, 
    "display_time": "2016-10-21T00:00:12", 
    "date": 1477033212000.0, 
    "dateString": "2016-10-21T00:00:12", 
    "device": "openaps://cgm", 
    "type": "sgv", 
    "glucose": 295
  }, 
  {
    "trend_arrow": "FLAT", 
    "system_time": "2016-10-21T06:54:50", 
    "direction": "Flat", 
    "sgv": 301, 
    "display_time": "2016-10-20T23:55:13", 
    "date": 1477032913000.0, 
    "dateString": "2016-10-20T23:55:13", 
    "device": "openaps://cgm", 
    "type": "sgv", 
    "glucose": 301
  }, 
  {
    "trend_arrow": "FLAT", 
    "system_time": "2016-10-21T06:49:51", 
    "direction": "Flat", 
    "sgv": 299, 
    "display_time": "2016-10-20T23:50:14", 
    "date": 1477032614000.0, 
    "dateString": "2016-10-20T23:50:14", 
    "device": "openaps://cgm", 
    "type": "sgv", 
    "glucose": 299
  }, 
  {
    "trend_arrow": "45_UP", 
    "system_time": "2016-10-21T06:44:50", 
    "direction": "FortyFiveUp", 
    "sgv": 298, 
    "display_time": "2016-10-20T23:45:13", 
    "date": 1477032313000.0, 
    "dateString": "2016-10-20T23:45:13", 
    "device": "openaps://cgm", 
    "type": "sgv", 
    "glucose": 298
  }, 
  {
    "trend_arrow": "45_UP", 
    "system_time": "2016-10-21T06:39:50", 
    "direction": "FortyFiveUp", 
    "sgv": 297, 
    "display_time": "2016-10-20T23:40:13", 
    "date": 1477032013000.0, 
    "dateString": "2016-10-20T23:40:13", 
    "device": "openaps://cgm", 
    "type": "sgv", 
    "glucose": 297
  }, 
  {
    "trend_arrow": "45_UP", 
    "system_time": "2016-10-21T06:34:52", 
    "direction": "FortyFiveUp", 
    "sgv": 291, 
    "display_time": "2016-10-20T23:35:15", 
    "date": 1477031715000.0, 
    "dateString": "2016-10-20T23:35:15", 
    "device": "openaps://cgm", 
    "type": "sgv", 
    "glucose": 291
  }, 
  {
    "trend_arrow": "FLAT", 
    "system_time": "2016-10-21T06:29:51", 
    "direction": "Flat", 
    "sgv": 280, 
    "display_time": "2016-10-20T23:30:14", 
    "date": 1477031414000.0, 
    "dateString": "2016-10-20T23:30:14", 
    "device": "openaps://cgm", 
    "type": "sgv", 
    "glucose": 280
  }, 
  {
    "trend_arrow": "45_DOWN", 
    "system_time": "2016-10-21T06:24:50", 
    "direction": "FortyFiveDown", 
    "sgv": 264, 
    "display_time": "2016-10-20T23:25:13", 
    "date": 1477031113000.0, 
    "dateString": "2016-10-20T23:25:13", 
    "device": "openaps://cgm", 
    "type": "sgv", 
    "glucose": 264
  }, 
  {
    "trend_arrow": "45_DOWN", 
    "system_time": "2016-10-21T06:19:51", 
    "direction": "FortyFiveDown", 
    "sgv": 267, 
    "display_time": "2016-10-20T23:20:13", 
    "date": 1477030813000.0, 
    "dateString": "2016-10-20T23:20:13", 
    "device": "openaps://cgm", 
    "type": "sgv", 
    "glucose": 267
  }, 
  {
    "trend_arrow": "45_DOWN", 
    "system_time": "2016-10-21T06:14:49", 
    "direction": "FortyFiveDown", 
    "sgv": 276, 
    "display_time": "2016-10-20T23:15:11", 
    "date": 1477030511000.0, 
    "dateString": "2016-10-20T23:15:11", 
    "device": "openaps://cgm", 
    "type": "sgv", 
    "glucose": 276
  }, 
  {
    "trend_arrow": "FLAT", 
    "system_time": "2016-10-21T06:09:49", 
    "direction": "Flat", 
    "sgv": 285, 
    "display_time": "2016-10-20T23:10:12", 
    "date": 1477030212000.0, 
    "dateString": "2016-10-20T23:10:12", 
    "device": "openaps://cgm", 
    "type": "sgv", 
    "glucose": 285
  }, 
  {
    "trend_arrow": "FLAT", 
    "system_time": "2016-10-21T06:04:51", 
    "direction": "Flat", 
    "sgv": 288, 
    "display_time": "2016-10-20T23:05:13", 
    "date": 1477029913000.0, 
    "dateString": "2016-10-20T23:05:13", 
    "device": "openaps://cgm", 
    "type": "sgv", 
    "glucose": 288
  }, 
  {
    "trend_arrow": "45_DOWN", 
    "system_time": "2016-10-21T05:59:53", 
    "direction": "FortyFiveDown", 
    "sgv": 291, 
    "display_time": "2016-10-20T23:00:16", 
    "date": 1477029616000.0, 
    "dateString": "2016-10-20T23:00:16", 
    "device": "openaps://cgm", 
    "type": "sgv", 
    "glucose": 291
  }, 
  {
    "trend_arrow": "45_DOWN", 
    "system_time": "2016-10-21T05:54:49", 
    "direction": "FortyFiveDown", 
    "sgv": 294, 
    "display_time": "2016-10-20T22:55:12", 
    "date": 1477029312000.0, 
    "dateString": "2016-10-20T22:55:12", 
    "device": "openaps://cgm", 
    "type": "sgv", 
    "glucose": 294
  }, 
  {
    "trend_arrow": "45_DOWN", 
    "system_time": "2016-10-21T05:49:49", 
    "direction": "FortyFiveDown", 
    "sgv": 299, 
    "display_time": "2016-10-20T22:50:12", 
    "date": 1477029012000.0, 
    "dateString": "2016-10-20T22:50:12", 
    "device": "openaps://cgm", 
    "type": "sgv", 
    "glucose": 299
  }, 
  {
    "trend_arrow": "45_DOWN", 
    "system_time": "2016-10-21T05:44:50", 
    "direction": "FortyFiveDown", 
    "sgv": 306, 
    "display_time": "2016-10-20T22:45:12", 
    "date": 1477028712000.0, 
    "dateString": "2016-10-20T22:45:12", 
    "device": "openaps://cgm", 
    "type": "sgv", 
    "glucose": 306
  }, 
  {
    "trend_arrow": "45_DOWN", 
    "system_time": "2016-10-21T05:39:52", 
    "direction": "FortyFiveDown", 
    "sgv": 314, 
    "display_time": "2016-10-20T22:40:14", 
    "date": 1477028414000.0, 
    "dateString": "2016-10-20T22:40:14", 
    "device": "openaps://cgm", 
    "type": "sgv", 
    "glucose": 314
  }, 
  {
    "trend_arrow": "45_DOWN", 
    "system_time": "2016-10-21T05:34:50", 
    "direction": "FortyFiveDown", 
    "sgv": 321, 
    "display_time": "2016-10-20T22:35:13", 
    "date": 1477028113000.0, 
    "dateString": "2016-10-20T22:35:13", 
    "device": "openaps://cgm", 
    "type": "sgv", 
    "glucose": 321
  }, 
  {
    "trend_arrow": "FLAT", 
    "system_time": "2016-10-21T05:29:53", 
    "direction": "Flat", 
    "sgv": 327, 
    "display_time": "2016-10-20T22:30:15", 
    "date": 1477027815000.0, 
    "dateString": "2016-10-20T22:30:15", 
    "device": "openaps://cgm", 
    "type": "sgv", 
    "glucose": 327
  }, 
  {
    "trend_arrow": "FLAT", 
    "system_time": "2016-10-21T05:24:50", 
    "direction": "Flat", 
    "sgv": 338, 
    "display_time": "2016-10-20T22:25:12", 
    "date": 1477027512000.0, 
    "dateString": "2016-10-20T22:25:12", 
    "device": "openaps://cgm", 
    "type": "sgv", 
    "glucose": 338
  }, 
  {
    "trend_arrow": "45_UP", 
    "system_time": "2016-10-21T05:19:51", 
    "direction": "FortyFiveUp", 
    "sgv": 342, 
    "display_time": "2016-10-20T22:20:13", 
    "date": 1477027213000.0, 
    "dateString": "2016-10-20T22:20:13", 
    "device": "openaps://cgm", 
    "type": "sgv", 
    "glucose": 342
  }, 
  {
    "trend_arrow": "45_UP", 
    "system_time": "2016-10-21T05:14:51", 
    "direction": "FortyFiveUp", 
    "sgv": 340, 
    "display_time": "2016-10-20T22:15:13", 
    "date": 1477026913000.0, 
    "dateString": "2016-10-20T22:15:13", 
    "device": "openaps://cgm", 
    "type": "sgv", 
    "glucose": 340
  }, 
  {
    "trend_arrow": "FLAT", 
    "system_time": "2016-10-21T05:09:55", 
    "direction": "Flat", 
    "sgv": 326, 
    "display_time": "2016-10-20T22:10:17", 
    "date": 1477026617000.0, 
    "dateString": "2016-10-20T22:10:17", 
    "device": "openaps://cgm", 
    "type": "sgv", 
    "glucose": 326
  }, 
  {
    "trend_arrow": "FLAT", 
    "system_time": "2016-10-21T05:04:50", 
    "direction": "Flat", 
    "sgv": 326, 
    "display_time": "2016-10-20T22:05:13", 
    "date": 1477026313000.0, 
    "dateString": "2016-10-20T22:05:13", 
    "device": "openaps://cgm", 
    "type": "sgv", 
    "glucose": 326
  }, 
  {
    "trend_arrow": "FLAT", 
    "system_time": "2016-10-21T04:59:52", 
    "direction": "Flat", 
    "sgv": 302, 
    "display_time": "2016-10-20T22:00:14", 
    "date": 1477026014000.0, 
    "dateString": "2016-10-20T22:00:14", 
    "device": "openaps://cgm", 
    "type": "sgv", 
    "glucose": 302
  }, 
  {
    "trend_arrow": "45_UP", 
    "system_time": "2016-10-21T04:54:50", 
    "direction": "FortyFiveUp", 
    "sgv": 302, 
    "display_time": "2016-10-20T21:55:13", 
    "date": 1477025713000.0, 
    "dateString": "2016-10-20T21:55:13", 
    "device": "openaps://cgm", 
    "type": "sgv", 
    "glucose": 302
  }, 
  {
    "trend_arrow": "45_UP", 
    "system_time": "2016-10-21T04:19:52", 
    "direction": "FortyFiveUp", 
    "sgv": 262, 
    "display_time": "2016-10-20T21:20:14", 
    "date": 1477023614000.0, 
    "dateString": "2016-10-20T21:20:14", 
    "device": "openaps://cgm", 
    "type": "sgv", 
    "glucose": 262
  }
]